mdxify/__init__.py
mdxify/__main__.py
mdxify/_version.py
mdxify/cli.py
mdxify/discovery.py
mdxify/formatter.py
mdxify/generator.py
mdxify/navigation.py
mdxify/parser.py
mdxify/py.typed
mdxify/renderers.py
mdxify/source_links.py
mdxify-0.2.35.dist-info/METADATA
mdxify-0.2.35.dist-info/WHEEL
mdxify-0.2.35.dist-info/entry_points.txt
mdxify-0.2.35.dist-info/RECORD
