Metadata-Version: 2.4
Name: mdxify
Version: 0.2.35
Summary: Generate MDX API documentation from Python modules
Project-URL: Code, https://github.com/zzstoatzz/mdxify
Author-email: zzstoatzz <thrast36@gmail.com>
License: MIT
Keywords: api,documentation,mdx,python
Classifier: Programming Language :: Python :: 3 :: Only
Classifier: Programming Language :: Python :: 3.10
Classifier: Programming Language :: Python :: 3.11
Classifier: Programming Language :: Python :: 3.12
Classifier: Topic :: Documentation
Classifier: Topic :: Software Development :: Documentation
Requires-Python: >=3.10
Requires-Dist: griffe>=0.36.0
